{
    "name": "servo-tutorials",
    "version": "0.0.1",
    "description": "",
    "dependencies": {
        "circuit-playground": "*",
        "servo": "*"
    },
    "files": [
        "main.blocks",
        "main.ts",
        "README.md",
        "positional-servo-tutorial.md",
        "Continuous-servo-tutorial.md"
    ],
    "testFiles": [
        "test.ts"
    ],
    "targetVersions": {
        "target": "1.6.8",
        "targetId": "adafruit"
    },
    "supportedTargets": [
        "adafruit"
    ],
    "preferredEditor": "tsprj"
}
